make_professional_website/__init__.py
make_professional_website/make_professional_website.py
make_professional_website/resume.html
make_professional_website-0.1.1.dist-info/METADATA
make_professional_website-0.1.1.dist-info/WHEEL
make_professional_website-0.1.1.dist-info/entry_points.txt
make_professional_website-0.1.1.dist-info/licenses/LICENSE
make_professional_website-0.1.1.dist-info/RECORD
