Metadata-Version: 2.3
Name: make-professional-website
Version: 0.1.1
Summary: A command-line interface tool to make a professional HTML website from YAML files.
Project-URL: Homepage, https://github.com/d3987ef8/make-professional-website
Project-URL: Issues, https://github.com/d3987ef8/make-professional-website/issues
Author-email: Jack Murray <contact@jackmurray.com>
License-File: LICENSE
Classifier: License :: OSI Approved :: MIT License
Classifier: Operating System :: OS Independent
Classifier: Programming Language :: Python :: 3
Requires-Python: >=3.9
Requires-Dist: jinja2
Requires-Dist: pyyaml
